aws_data_landing_zone/__init__.py
aws_data_landing_zone/py.typed
aws_data_landing_zone/_jsii/__init__.py
aws_data_landing_zone/_jsii/aws-data-landing-zone@0.1.1.jsii.tgz
aws_data_landing_zone-0.1.1.dist-info/LICENSE
aws_data_landing_zone-0.1.1.dist-info/METADATA
aws_data_landing_zone-0.1.1.dist-info/WHEEL
aws_data_landing_zone-0.1.1.dist-info/top_level.txt
aws_data_landing_zone-0.1.1.dist-info/RECORD
